Lab01/design/full_adder/half_adder.v
module half_adder (
    output s, 
    output c, 
    input a, 
    input b
);
    assign s = a^b;
    assign c = a&b;
endmodule

Lab01/design/full_adder/full_adder.v
module full_adder(
    input a, b, c,
    output s, carry
);
    wire s1;
    wire c1;
    wire c2;

    half_adder hf1(
        .a(a),
        .b(b),
        .s(s1),
        .c(c1)
    );

    half_adder hf2(
        .a(s1),
        .b(c),
        .s(s),
        .c(c2)
    );

    assign carry = c1 | c2;


endmodule

Lab01/design/full_adder/full_adder_tb.v
`timescale 1ns/1ps
module full_adder_tb;
    reg a;
    reg b;
    reg c;

    wire s;
    wire carry;

    full_adder uut(
        .a(a),
        .b(b),
        .c(c),
        .s(s),
        .carry(carry)
    );

    initial begin
        $dumpfile("full_adder.vcd");
        $dumpvars(0, full_adder_tb);

        {a,b,c}=3'b000;

        #2 {a,b,c}=3'b001;
        #2 {a,b,c}=3'b010;
        #2 {a,b,c}=3'b011;
        #2 {a,b,c}=3'b100;
        #2 {a,b,c}=3'b101;
        #2 {a,b,c}=3'b110;
        #2 {a,b,c}=3'b111;

        #20 $finish;
        
    end

    initial $monitor("time = %g, a=%b, b=%b, c=%b, sum=%b, carry=%b",$time, a,b,c,s,carry);

    
endmodule

Lab01/design/full_adder/full_adder.vcd
$date
	Tue Mar 10 21:25:08 2026
$end
$version
	Icarus Verilog
$end
$timescale
	1ps
$end
$scope module full_adder_tb $end
$var wire 1 ! s $end
$var wire 1 " carry $end
$var reg 1 # a $end
$var reg 1 $ b $end
$var reg 1 % c $end
$scope module uut $end
$var wire 1 # a $end
$var wire 1 $ b $end
$var wire 1 % c $end
$var wire 1 " carry $end
$var wire 1 & s1 $end
$var wire 1 ! s $end
$var wire 1 ' c2 $end
$var wire 1 ( c1 $end
$scope module hf1 $end
$var wire 1 # a $end
$var wire 1 $ b $end
$var wire 1 ( c $end
$var wire 1 & s $end
$upscope $end
$scope module hf2 $end
$var wire 1 & a $end
$var wire 1 % b $end
$var wire 1 ' c $end
$var wire 1 ! s $end
$upscope $end
$upscope $end
$upscope $end
$enddefinitions $end
#0
$dumpvars
0(
0'
0&
0%
0$
0#
0"
0!
$end
#2000
1!
1%
#4000
1&
1!
1$
0%
#6000
1"
0!
1'
1%
#8000
0"
1!
0'
1#
0$
0%
#10000
1"
0!
1'
1%
#12000
0&
1(
0!
0'
1$
0%
#14000
1!
1%
