Lab01/design/ripple_counter/d_ff.v
module d_ff (
    input clk, d, rst,
    output reg q
);

    always @(negedge clk or posedge rst) begin
        if (rst) begin
            q<=1'b0;
        end
       else begin
            q <= d; 
        end
    end

    
endmodule

Lab01/design/ripple_counter/d_ff_tb.v
`timescale 1ns/1ps
module d_ff_tb;
    reg d;
    reg clk;
    reg reset;
    wire q;
    
    d_ff uut(
        .d(d),
        .clk(clk),
        .q(q),
        .rst(reset)
    );

    always #5 clk = ~clk;

    initial begin
        $dumpfile("d_ff.vcd");
        $dumpvars(0, d_ff_tb);

        // initially clk=0;
        clk =0;
        reset=0;
        d=0;

        #10 d = 1; // Change D after first posedge
        #10 d = 0;
        #10 d = 1;

        #5 reset=1;
        
        #10 $finish;

    end

    initial $monitor("time=%g, rst=%b, clk=%b, d=%b, q=%b", $time, reset, clk, d, q);

endmodule

Lab01/design/ripple_counter/d_ff.vcd
$date
	Wed Mar 11 07:00:19 2026
$end
$version
	Icarus Verilog
$end
$timescale
	1ps
$end
$scope module d_ff_tb $end
$var wire 1 ! q $end
$var reg 1 " clk $end
$var reg 1 # d $end
$var reg 1 $ reset $end
$scope module uut $end
$var wire 1 " clk $end
$var wire 1 # d $end
$var wire 1 $ rst $end
$var reg 1 ! q $end
$upscope $end
$upscope $end
$enddefinitions $end
#0
$dumpvars
0$
0#
0"
x!
$end
#5000
0!
1"
#10000
0"
1#
#15000
1!
1"
#20000
0"
0#
#25000
0!
1"
#30000
0"
1#
#35000
1"
1$
