Lab01/design/ripple_counter/d_ff.v
module d_ff (
    input clk, d, rst,
    output reg q
);

    always @(negedge clk or posedge rst) begin
        if (rst) begin
            q<=1'b0;
        end
       else begin
            q <= d; 
        end
    end

    
endmodule

Lab01/design/ripple_counter/t_ff.v
// `include "d_ff.v"
module t_ff (
    input clk, rst,
    output q
);

    wire d;

    d_ff uut(
        .clk(clk),
        .rst(rst),
        .d(d),
        .q(q)
    );

    assign d = ~q;
    
endmodule

Lab01/design/ripple_counter/ripple_counter.v
// `include "t_ff.v"

module ripple_counter (
    input clk, rst,
    output [3:0] q
);
    t_ff t0(
        .clk(clk),
        .rst(rst),
        .q(q[0])
    );
    t_ff t1(
        .clk(q[0]),
        .rst(rst),
        .q(q[1])
    );
    t_ff t2(
        .clk(q[1]),
        .rst(rst),
        .q(q[2])
    );
    t_ff t3(
        .clk(q[2]),
        .rst(rst),
        .q(q[3])
    );
    
endmodule

Lab01/design/ripple_counter/tb_ripple_counter.v
`include "ripple_counter.v"
`timescale 1ns/1ps
module tb_ripple_counter;
    reg clk;
    reg rst;
    wire [3:0] q;

    ripple_counter r1
    (
        .rst(rst),
        .q(q),
        .clk(clk)
    );

    always #5 clk = ~clk;



    initial begin
        $dumpfile("tb_ripple_counter.vcd");
        $dumpvars(0, tb_ripple_counter);
    end

    initial begin
        // run with no reset
        clk = 0;
        rst = 1;
        #10;
        rst=0; #5;
        


        #200;
        $finish;


    end
    
    always @(negedge clk) begin
        $display("%d \t %h \t %b", q, q, q);
    end

endmodule

Lab01/design/ripple_counter/tb_ripple_counter.vcd
$date
	Fri Mar 13 07:50:05 2026
$end
$version
	Icarus Verilog
$end
$timescale
	1ps
$end
$scope module tb_ripple_counter $end
$var wire 4 ! q [3:0] $end
$var reg 1 " clk $end
$var reg 1 # rst $end
$scope module r1 $end
$var wire 1 " clk $end
$var wire 1 # rst $end
$var wire 4 $ q [3:0] $end
$scope module t0 $end
$var wire 1 " clk $end
$var wire 1 % d $end
$var wire 1 # rst $end
$var wire 1 & q $end
$scope module uut $end
$var wire 1 " clk $end
$var wire 1 % d $end
$var wire 1 # rst $end
$var reg 1 & q $end
$upscope $end
$upscope $end
$scope module t1 $end
$var wire 1 ' clk $end
$var wire 1 ( d $end
$var wire 1 # rst $end
$var wire 1 ) q $end
$scope module uut $end
$var wire 1 ' clk $end
$var wire 1 ( d $end
$var wire 1 # rst $end
$var reg 1 ) q $end
$upscope $end
$upscope $end
$scope module t2 $end
$var wire 1 * clk $end
$var wire 1 + d $end
$var wire 1 # rst $end
$var wire 1 , q $end
$scope module uut $end
$var wire 1 * clk $end
$var wire 1 + d $end
$var wire 1 # rst $end
$var reg 1 , q $end
$upscope $end
$upscope $end
$scope module t3 $end
$var wire 1 - clk $end
$var wire 1 . d $end
$var wire 1 # rst $end
$var wire 1 / q $end
$scope module uut $end
$var wire 1 - clk $end
$var wire 1 . d $end
$var wire 1 # rst $end
$var reg 1 / q $end
$upscope $end
$upscope $end
$upscope $end
$upscope $end
$enddefinitions $end
#0
$dumpvars
0/
1.
0-
0,
1+
0*
0)
1(
0'
0&
1%
b0 $
1#
0"
b0 !
$end
#5000
1"
#10000
0%
1'
b1 !
b1 $
1&
0"
0#
#15000
1"
#20000
0(
1*
1)
1%
0'
b10 !
b10 $
0&
0"
#25000
1"
#30000
0%
1'
b11 !
b11 $
1&
0"
#35000
1"
#40000
0+
1-
1,
1(
0*
0)
1%
0'
b100 !
b100 $
0&
0"
#45000
1"
#50000
0%
1'
b101 !
b101 $
1&
0"
#55000
1"
#60000
0(
1*
1)
1%
0'
b110 !
b110 $
0&
0"
#65000
1"
#70000
0%
1'
b111 !
b111 $
1&
0"
#75000
1"
#80000
0.
1/
1+
0-
0,
1(
0*
0)
1%
0'
b1000 !
b1000 $
0&
0"
#85000
1"
#90000
0%
1'
b1001 !
b1001 $
1&
0"
#95000
1"
#100000
0(
1*
1)
1%
0'
b1010 !
b1010 $
0&
0"
#105000
1"
#110000
0%
1'
b1011 !
b1011 $
1&
0"
#115000
1"
#120000
0+
1-
1,
1(
0*
0)
1%
0'
b1100 !
b1100 $
0&
0"
#125000
1"
#130000
0%
1'
b1101 !
b1101 $
1&
0"
#135000
1"
#140000
0(
1*
1)
1%
0'
b1110 !
b1110 $
0&
0"
#145000
1"
#150000
0%
1'
b1111 !
b1111 $
1&
0"
#155000
1"
#160000
1.
0/
1+
0-
0,
1(
0*
0)
1%
0'
b0 !
b0 $
0&
0"
#165000
1"
#170000
0%
1'
b1 !
b1 $
1&
0"
#175000
1"
#180000
0(
1*
1)
1%
0'
b10 !
b10 $
0&
0"
#185000
1"
#190000
0%
1'
b11 !
b11 $
1&
0"
#195000
1"
#200000
0+
1-
1,
1(
0*
0)
1%
0'
b100 !
b100 $
0&
0"
#205000
1"
#210000
0%
1'
b101 !
b101 $
1&
0"
