single_cycle_risc/instruction_decoder.v
module instruction_decoder (
    input [31:0] instruction,

    output [6:0] opcode,
    output [4:0] rd,
    output [2:0] func3,
    output [4:0] rs1,
    output [4:0] rs2,
    output [6:0] func7

);

    assign opcode = instruction[6:0];
    assign rd = instruction[11:7];
    assign func3 = instruction[14:12];
    assign rs1 = instruction[19:15];
    assign rs2 = instruction[24:20];
    assign func7 = instruction[31:25];

    
endmodule

Lab01/design/tb_instruction_decoder.v
`timescale 1ns/1ps
`include "instruction_decoder.v"
`default_nettype none

module tb_instruction_decoder;
    reg [31:0] instruction;
    wire [6:0] opcode;
    wire [4:0] rd;
    wire [2:0] func3;
    wire [4:0] rs1;
    wire [4:0] rs2;
    wire [6:0] func7;

    instruction_decoder uut
    (
        .instruction(instruction),
        .opcode(opcode),
        .rd(rd),
        .func3(func3),
        .rs1(rs1),
        .rs2(rs2),
        .func7(func7)
    );

    initial begin
        $dumpfile("tb_instruction_decoder.vcd");
        $dumpvars(0, tb_instruction_decoder);

        // Test cases
        // Inst Name FMT Opcode funct3 funct7 Description (C) Note
        // add ADD R 0110011 0x0 0x00 rd = rs1 + rs2
        // sub SUB R 0110011 0x0 0x20 rd = rs1 - rs2
        // xor XOR R 0110011 0x4 0x00 rd = rs1 ˆ rs2
        // or OR R 0110011 0x6 0x00 rd = rs1 | rs2
        // and AND R 0110011 0x7 0x00 rd = rs1 & rs2
        // sll Shift Left Logical R 0110011 0x1 0x00 rd = rs1 << rs2
        // srl Shift Right Logical R 0110011 0x5 0x00 rd = rs1 >> rs2
        // sra Shift Right Arith* R 0110011 0x5 0x20 rd = rs1 >> rs2 msb-extends
        // slt Set Less Than R 0110011 0x2 0x00 rd = (rs1 < rs2)?1:0
        // sltu Set Less Than (U) R 0110011 0x3 0x00 rd = (rs1 < rs2)?1:0 zero-extends
        // using x20 for destination x21 as source 1 and x22 as source 2 for all test cases
        instruction = 32'b0000000_10110_10101_000_10100_0110011; // add x20, x21, x22
        #10;
        instruction = 32'b0100000_10110_10101_000_10100_0110011; // sub x20, x21, x22
        #10;
        instruction = 32'b0000000_10110_10101_100_10100_0110011; // xor x20, x21, x22
        #10;
        instruction = 32'b0000000_10110_10101_110_10100_0110011; // or x20, x21, x22
        #10;
        instruction = 32'b0000000_10110_10101_111_10100_0110011; // and x20, x21, x22
        #10;
        instruction = 32'b0000000_10110_10101_001_10100_0110011; // sll x20, x21, x22
        #10;
        instruction = 32'b0000000_10110_10101_101_10100_0110011; // srl x20, x21, x22
        #10;
        instruction = 32'b0100000_10110_10101_101_10100_0110011; // sra x20, x21, x22
        #10;
        instruction = 32'b0000000_10110_10101_010_10100_0110011; // slt x20, x21, x22
        #10;
        instruction = 32'b0000000_10110_10101_011_10100_0110011; // sltu x20, x21, x22
        #10;
        $finish;
    end

endmodule
`default_nettype wire

Lab01/design/tb_instruction_decoder.vcd
$date
	Sun Mar 15 07:59:58 2026
$end
$version
	Icarus Verilog
$end
$timescale
	1ps
$end
$scope module tb_instruction_decoder $end
$var wire 5 ! rs2 [4:0] $end
$var wire 5 " rs1 [4:0] $end
$var wire 5 # rd [4:0] $end
$var wire 7 $ opcode [6:0] $end
$var wire 7 % func7 [6:0] $end
$var wire 3 & func3 [2:0] $end
$var reg 32 ' instruction [31:0] $end
$scope module uut $end
$var wire 32 ( instruction [31:0] $end
$var wire 5 ) rs2 [4:0] $end
$var wire 5 * rs1 [4:0] $end
$var wire 5 + rd [4:0] $end
$var wire 7 , opcode [6:0] $end
$var wire 7 - func7 [6:0] $end
$var wire 3 . func3 [2:0] $end
$upscope $end
$upscope $end
$enddefinitions $end
#0
$dumpvars
b0 .
b0 -
b110011 ,
b10100 +
b10101 *
b10110 )
b1011010101000101000110011 (
b1011010101000101000110011 '
b0 &
b0 %
b110011 $
b10100 #
b10101 "
b10110 !
$end
#10000
b100000 %
b100000 -
b1000001011010101000101000110011 '
b1000001011010101000101000110011 (
#20000
b100 &
b100 .
b0 %
b0 -
b1011010101100101000110011 '
b1011010101100101000110011 (
#30000
b110 &
b110 .
b1011010101110101000110011 '
b1011010101110101000110011 (
#40000
b111 &
b111 .
b1011010101111101000110011 '
b1011010101111101000110011 (
#50000
b1 &
b1 .
b1011010101001101000110011 '
b1011010101001101000110011 (
#60000
b101 &
b101 .
b1011010101101101000110011 '
b1011010101101101000110011 (
#70000
b100000 %
b100000 -
b1000001011010101101101000110011 '
b1000001011010101101101000110011 (
#80000
b10 &
b10 .
b0 %
b0 -
b1011010101010101000110011 '
b1011010101010101000110011 (
#90000
b11 &
b11 .
b1011010101011101000110011 '
b1011010101011101000110011 (
