Lab01/design/two_one_mux.v
// 2 bit 2:1 MUX
module two_one_mux (
    input [1:0] A,
    input [1:0] B,
    input sel,
    output wire [1:0] q
);

    //assign q = (sel) ? B : A;

    always @(sel) begin
        case (sel)
            1'b0: q = A;
            1'b1: q = B;
            default: q = 2'bxx;
        endcase
    end
    
endmodule


// 1 bit 2:1 mux
// module two_one_mux (
//     input [1:0] d, sel,
//     output reg q
// );
//     always @(sel) begin
//         case (sel)
//             1'b0 : q = d[0];
//             1'b1 : q = d[1];
//             default: q =  1'bx;
//         endcase
//     end
    
// endmodule

Lab01/design/two_one_mux_tb.v
`timescale 1ns/1ps
module two_one_mux_tb;
    reg [1:0] A;
    reg [1:0] B;
    reg sel;
    wire [1:0] q ;

    two_one_mux uut(
        .A(A),
        .B(B),
        .sel(sel),
        .q(q)
    );

    always #5 sel = ~ sel;

    initial begin
        $dumpfile("two_one_mux_tb.vcd");
        $dumpvars(0, two_one_mux_tb); 

        // initialize sel, A and B
        sel=0;
        A =  2'b11;
        B = 2'b00;
        #10;

        A = 2'b10;
        B = 2'b11;

        #20;
        A = 2'b00;
        B = 2'b10;

        #120;

        $finish;

    end

    initial $monitor("time=%g, sel=%b, A=%b, B=%b, q=%b", $time, sel, A, B, q);

endmodule

Lab01/design/two_one_mux_tb.vcd
$date
	Sat Mar 14 20:43:01 2026
$end
$version
	Icarus Verilog
$end
$timescale
	1ps
$end
$scope module two_one_mux_tb $end
$var wire 2 ! q [1:0] $end
$var reg 2 " A [1:0] $end
$var reg 2 # B [1:0] $end
$var reg 1 $ sel $end
$scope module uut $end
$var wire 2 % A [1:0] $end
$var wire 2 & B [1:0] $end
$var wire 1 $ sel $end
$var wire 2 ' q [1:0] $end
$upscope $end
$upscope $end
$enddefinitions $end
#0
$dumpvars
b11 '
b0 &
b11 %
0$
b0 #
b11 "
b11 !
$end
#5000
b0 !
b0 '
1$
#10000
b10 !
b10 '
0$
b11 #
b11 &
b10 "
b10 %
#15000
b11 !
b11 '
1$
#20000
b10 !
b10 '
0$
#25000
b11 !
b11 '
1$
#30000
b0 !
b0 '
0$
b10 #
b10 &
b0 "
b0 %
#35000
b10 !
b10 '
1$
#40000
b0 !
b0 '
0$
#45000
b10 !
b10 '
1$
#50000
b0 !
b0 '
0$
#55000
b10 !
b10 '
1$
#60000
b0 !
b0 '
0$
#65000
b10 !
b10 '
1$
#70000
b0 !
b0 '
0$
#75000
b10 !
b10 '
1$
#80000
b0 !
b0 '
0$
#85000
b10 !
b10 '
1$
#90000
b0 !
b0 '
0$
#95000
b10 !
b10 '
1$
#100000
b0 !
b0 '
0$
#105000
b10 !
b10 '
1$
#110000
b0 !
b0 '
0$
#115000
b10 !
b10 '
1$
#120000
b0 !
b0 '
0$
#125000
b10 !
b10 '
1$
#130000
b0 !
b0 '
0$
#135000
b10 !
b10 '
1$
#140000
b0 !
b0 '
0$
#145000
b10 !
b10 '
1$
#150000
b0 !
b0 '
0$
